lightgbm_feature_importance_evaluator_zhoumath/__init__.py
lightgbm_feature_importance_evaluator_zhoumath/evaluator.py
lightgbm_feature_importance_evaluator_zhoumath/utils.py
test/__init__.py
test/test_evaluator.py
lightgbm_feature_importance_evaluator_zhoumath-0.1.1.dist-info/LICENSE
lightgbm_feature_importance_evaluator_zhoumath-0.1.1.dist-info/METADATA
lightgbm_feature_importance_evaluator_zhoumath-0.1.1.dist-info/WHEEL
lightgbm_feature_importance_evaluator_zhoumath-0.1.1.dist-info/top_level.txt
lightgbm_feature_importance_evaluator_zhoumath-0.1.1.dist-info/RECORD
