Metadata-Version: 2.1
Name: lightgbm_feature_importance_evaluator_zhoumath
Version: 0.1.1
Summary: Evaluate feature importance for LightGBM models using various methods.
Home-page: https://github.com/shanghaizhoushus/lightgbm_feature_importance_evaluator_zhoumath
Author: Zhoushus
Author-email: zhoushus@foxmail.com
Classifier: Programming Language :: Python :: 3
Classifier: License :: OSI Approved :: MIT License
Classifier: Operating System :: OS Independent
Requires-Python: >=3.6
License-File: LICENSE
Requires-Dist: numpy
Requires-Dist: pandas
Requires-Dist: scikit-learn
Requires-Dist: shap
Requires-Dist: lightgbm
